{
 "accept_payment": 0,
 "allow_comments": 0,
 "allow_delete": 0,
 "allow_edit": 1,
 "allow_incomplete": 0,
 "allow_multiple": 0,
 "allow_print": 0,
 "amount": 0.0,
 "amount_based_on_field": 0,
 "button_label": "Save",
 "creation": "2022-07-01 22:25:11.929313",
 "currency": "HNL",
 "desk_form_fields": [
  {
   "allow_read_on_all_link_options": 1,
   "default": "",
   "depends_on": "",
   "description": "",
   "fieldname": "parent",
   "fieldtype": "Data",
   "hidden": 0,
   "label": "POS Profile",
   "max_length": 0,
   "max_value": 0,
   "read_only": 1,
   "reqd": 0,
   "show_in_filter": 0
  },
  {
   "allow_read_on_all_link_options": 1,
   "default": "",
   "depends_on": "",
   "description": "",
   "fieldname": "parenttype",
   "fieldtype": "Data",
   "hidden": 1,
   "label": "POS Profile",
   "max_length": 0,
   "max_value": 0,
   "read_only": 1,
   "reqd": 0,
   "show_in_filter": 0
  },
  {
   "allow_read_on_all_link_options": 1,
   "default": "",
   "depends_on": "",
   "description": "",
   "fieldtype": "Column Break",
   "hidden": 0,
   "max_length": 0,
   "max_value": 0,
   "read_only": 0,
   "reqd": 0,
   "show_in_filter": 0
  },
  {
   "allow_read_on_all_link_options": 1,
   "default": "",
   "depends_on": "",
   "description": "",
   "fieldname": "user",
   "fieldtype": "Data",
   "hidden": 0,
   "label": "User",
   "max_length": 0,
   "max_value": 0,
   "options": "User",
   "read_only": 0,
   "reqd": 0,
   "show_in_filter": 0
  },
  {
   "allow_read_on_all_link_options": 1,
   "default": "",
   "depends_on": "",
   "description": "",
   "fieldtype": "Section Break",
   "hidden": 0,
   "max_length": 0,
   "max_value": 0,
   "read_only": 0,
   "reqd": 0,
   "show_in_filter": 0
  },
  {
   "allow_read_on_all_link_options": 1,
   "default": "",
   "depends_on": "",
   "description": "",
   "fieldname": "restaurant_permissions",
   "fieldtype": "Table",
   "hidden": 0,
   "label": "Restaurant Permission",
   "max_length": 0,
   "max_value": 0,
   "options": "Restaurant Permission",
   "read_only": 0,
   "reqd": 0,
   "show_in_filter": 0
  }
 ],
 "doc_type": "POS Profile User",
 "docstatus": 0,
 "doctype": "Desk Form",
 "idx": 0,
 "is_standard": 1,
 "login_required": 1,
 "max_attachment_size": 0,
 "modified": "2022-07-09 16:13:07.069646",
 "modified_by": "Administrator",
 "module": "Restaurant Management",
 "name": "restaurant-permission-manage",
 "owner": "Administrator",
 "payment_button_label": "Buy Now",
 "published": 1,
 "route": "restaurant-permission-manage",
 "route_to_success_link": 0,
 "show_attachments": 0,
 "show_in_grid": 0,
 "show_sidebar": 0,
 "sidebar_items": [],
 "title": "Restaurant Permission Manage"
}